{"data":{"site":{"meta":{"title":"CFP Land","description":"Calls for Proposals, Tech Conferences, and Speaking Tips","url":"https://www.cfpland.com","author":"Karl L. Hughes","twitter":"cfp_land","image":"/img/default.png"}},"conferences":{"edges":[{"node":{"id":"96da16fa-8391-5eb7-acdd-dd05179c18f4","data":{"name":"Rome .NET Conference 2020","event_url":"http://www.dotnetconf.it","location":"Via Avignone, 10, 00144 Roma RM","event_start_date":"2020-10-23","cfp_due_date":"2020-03-31","cfp_url":"https://sessionize.com/rome-dotnetconf-2020/","event_end_date":"2020-10-23","twitter":null,"perks_checked":true,"region":"Europe","subregion":"Southern Europe","icon":[{"url":"https://dl.airtable.com/.attachments/bc01f65d09df30f097646fcb2b2b38c8/8c279524/reserved.jpg"}],"city":null,"country":"Italy","created_date":"2020-02-18T00:20:46.000Z","created_days_back":160,"cfp_days_until":-118,"is_new":0,"description":"-","travel_covered":null,"hotel_covered":null,"stipend_covered":null,"record_id":"recqJ6XslGV70N4NR","category":[{"id":"526da865-5b6e-524b-942e-240033174fda","data":{"name":".NET","description":".NET and C# programming language conferences."},"fields":{"slug":"conferences/.net"}}]}}}]}},"pageContext":{"isCreatedByStatefulCreatePages":false,"recordId":"recqJ6XslGV70N4NR","relatedRecords":[{"name":"Asturias Netconf 2020","event_url":"http://asturiasnetconf.tech","location":"Gijón","event_start_date":"2020-02-22","cfp_due_date":"2019-12-16","cfp_url":"https://papercall.io/cfps/2758/submissions/new","event_end_date":"2020-02-22","twitter":null,"perks_checked":true,"region":"Europe","subregion":"Southern Europe","icon":[{"url":"https://dl.airtable.com/.attachments/d535416ac8ac2a8f52860dfe503c211c/197b1365/007-world.svg"}],"country":"Spain","created_date":"2019-11-25T04:20:30.000Z","created_days_back":245,"cfp_days_until":-224,"is_new":0,"description":"Asturias NetConf tendrá lugar el sábado 22 de Febrero en la EPI de Gijón. Durante la mañana se juntara a estudiantes, profesionales, apasionados e interesados en el mundo Microsoft y sus tecnologías, alrededor de charlas y una mesa redonda.","travel_covered":null,"hotel_covered":null,"stipend_covered":null,"record_id":"receFhUkzUZhxC3LE","category":[{"id":"526da865-5b6e-524b-942e-240033174fda","data":{"name":".NET","description":".NET and C# programming language conferences."},"fields":{"slug":"conferences/.net"}}],"score":5},{"name":"Power BI Portugal Day","event_url":"http://powerbiportugal.com/powerbiday","location":"Universidade NOVA de Lisboa","event_start_date":"2020-04-30","cfp_due_date":"2020-03-20","cfp_url":"https://sessionize.com/powerbi-portugal-day/","event_end_date":"2020-04-30","twitter":null,"perks_checked":true,"region":"Europe","subregion":"Southern Europe","icon":null,"country":"Portugal","created_date":"2020-02-07T08:21:07.000Z","created_days_back":171,"cfp_days_until":-129,"is_new":0,"description":null,"travel_covered":null,"hotel_covered":null,"stipend_covered":null,"record_id":"recJhs9lW01zxV2xr","category":[{"id":"526da865-5b6e-524b-942e-240033174fda","data":{"name":".NET","description":".NET and C# programming language conferences."},"fields":{"slug":"conferences/.net"}}],"score":5},{"name":"jsday 2020","event_url":"https://2020.jsday.it","location":"Hotel San Marco, Verona","event_start_date":"2020-05-12","cfp_due_date":"2019-12-31","cfp_url":"https://cfp.jsday.it/","event_end_date":"2020-05-13","twitter":null,"perks_checked":true,"region":"Europe","subregion":"Southern Europe","icon":[{"url":"https://dl.airtable.com/.attachments/f77d0c52312e86a05c6add94b36f32de/c5fe3b77/favicon.png"}],"country":"Italy","created_date":"2019-11-18T00:20:53.000Z","created_days_back":252,"cfp_days_until":-209,"is_new":0,"description":"The first international conference on JavaScript in Italy. May 12th-13th 2020 — Verona, Italy.","travel_covered":true,"hotel_covered":true,"stipend_covered":null,"record_id":"recRaQ5lopWrmXRDZ","category":[{"id":"1d79004c-a91c-56b6-812c-a72fd277e65e","data":{"name":"Javascript","description":"Frontend and backend Javascript conferences."},"fields":{"slug":"conferences/javascript"}}],"score":5},{"name":"QtDay","event_url":"https://www.qtday.it","location":"Florence, Italy","event_start_date":"2020-03-13","cfp_due_date":"2020-01-01","cfp_url":"https://www.papercall.io/qtday2020","event_end_date":null,"twitter":null,"perks_checked":null,"region":"Europe","subregion":"Southern Europe","icon":[{"url":"https://dl.airtable.com/.attachments/72679443315ff4b844cd7826b9b26ad0/19171441/qtday.it"}],"country":"Italy","created_date":"2020-02-10T14:07:50.000Z","created_days_back":167,"cfp_days_until":-208,"is_new":0,"description":"QtDay 2020. The international conference dedicated to Qt framework. The only event of its kind in Italy. Let’s make something great together.","travel_covered":null,"hotel_covered":null,"stipend_covered":null,"record_id":"recwj3TtX2RsvVqT0","category":[{"id":"17bb4611-8120-5f31-9bd1-7eabfa555d30","data":{"name":"General","description":"Conferences covering a wide range of web development and software engineering topics."},"fields":{"slug":"conferences/general"}}],"score":5}]}}