{"data":{"site":{"meta":{"title":"CFP Land","description":"Calls for Proposals, Tech Conferences, and Speaking Tips","url":"https://www.cfpland.com","author":"Karl L. Hughes","twitter":"cfp_land","image":"/img/default.png"}},"category":{"edges":[{"node":{"id":"fdc441fe-c4ba-5a1c-945c-b23eff87414b","data":{"name":"Data","description":"Machine learning, AI, Databases, and Big Data conferences."}}}]},"conferences":{"edges":[{"node":{"id":"a73f5b97-e526-526b-a4ca-7b96389692f9","data":{"name":"Data Day Monterrey 2019","event_url":"https://sg.com.mx/dataday","location":"Monterrey, Mexico","event_start_date":"2019-11-13","cfp_due_date":"2019-08-31","cfp_url":"https://papercall.io/cfps/2455/submissions/new","event_end_date":"2019-11-13","twitter":null,"perks_checked":true,"region":"Americas","subregion":"Central America","icon":[{"url":"https://dl.airtable.com/.attachments/5c74b3aa313ff3ac1c971e969d829131/977901bc/cropped-dataday-card-1.jpg"}],"country":"Mexico","created_date":"2019-08-24T04:20:39.000Z","created_days_back":5,"cfp_days_until":0,"is_new":1,"description":"El congreso líder de ciencia de datos en México con tres tracks: estrategia, ciencia de datos e ingeniería de datos.","travel_covered":true,"hotel_covered":true,"stipend_covered":null,"record_id":"recRoIobDBCvhr62p","category":[{"id":"fdc441fe-c4ba-5a1c-945c-b23eff87414b","data":{"name":"Data","description":"Machine learning, AI, Databases, and Big Data conferences."},"fields":{"slug":"conferences/data"}}]}}},{"node":{"id":"a1b8d318-aa39-58ec-aa51-288a36c84500","data":{"name":"Nerdzão #185 - MongoDB & Redis","event_url":"https://www.meetup.com/Nerdzao/events/264391761","location":"LinkApi  R. Geraldo Flausino Gomes, 78 · São Paulo","event_start_date":"2019-09-11","cfp_due_date":"2019-09-04","cfp_url":"https://docs.google.com/forms/d/e/1FAIpQLSfEb35Pk5F-_pFHl_MCkNx97HG_dgKgWbiydfP9MZ8C8mzITQ/viewform","event_end_date":null,"twitter":null,"perks_checked":true,"region":"Americas","subregion":"South America","icon":[{"url":"https://dl.airtable.com/.attachments/67aef74e674b21a398cc42589913d4ca/e49e79d0/m_swarm_196x196.b5c9ccb2.png"}],"country":"Brazil","created_date":"2019-08-29T16:49:36.000Z","created_days_back":0,"cfp_days_until":4,"is_new":1,"description":"Nesse encontro PRESENCIAL e GRATUITO, vamos falar sobre os bancos de dados MongoDB e Redis.\nCada palestrante terá entre 15 ou 30 minutos. NÃO ESQUEÇA DE CONFIRMAR OS DADOS NO LINK ABAIXO: A apresentação do DOCUMENTO é OBRIGATÓRIA para a participação, informe no momento do cadastro no evento no seg…","travel_covered":null,"hotel_covered":null,"stipend_covered":null,"record_id":"rec18tWZoeVf3IAdl","category":[{"id":"fdc441fe-c4ba-5a1c-945c-b23eff87414b","data":{"name":"Data","description":"Machine learning, AI, Databases, and Big Data conferences."},"fields":{"slug":"conferences/data"}}]}}}]}},"pageContext":{"isCreatedByStatefulCreatePages":false,"slug":"conferences/data"}}