{"data":{"site":{"meta":{"title":"CFP Land","description":"Calls for Proposals, Tech Conferences, and Speaking Tips","url":"https://www.cfpland.com","author":"Karl L. Hughes","twitter":"cfp_land","image":"/img/default.png"}},"conferences":{"edges":[{"node":{"id":"e2630ecb-0571-54d5-8972-1be24e36864c","data":{"name":"OpenSIPS Summit 2020","event_url":"https://www.opensips.org/events/Summit-2020Amsterdam","location":"Amsterdam, The Netherland","event_start_date":"2020-05-05","cfp_due_date":"2020-02-03","cfp_url":"https://papercall.io/cfps/2695/submissions/new","event_end_date":"2020-05-05","twitter":null,"perks_checked":true,"region":"Americas","subregion":"Northern America","icon":[{"url":"https://dl.airtable.com/.attachments/38a308924db046c01ddf938d18a23a99/ca484a10/opensips.org"}],"city":"New York","country":"United States","created_date":"2019-12-23T00:20:47.000Z","created_days_back":204,"cfp_days_until":-162,"is_new":0,"description":"More than 20 slots are available for speakers from all over the world, developers, managers/leaders or C-level. They will cover the 30 minutes slots with presentation over technical aspects, integration challenges or solution overviews. Their topics are not OpenSIPS centric, but also tackling other …","travel_covered":null,"hotel_covered":null,"stipend_covered":null,"record_id":"rech4VeafLA2qBwkE","category":[{"id":"17bb4611-8120-5f31-9bd1-7eabfa555d30","data":{"name":"General","description":"Conferences covering a wide range of web development and software engineering topics."},"fields":{"slug":"conferences/general"}}]}}}]}},"pageContext":{"isCreatedByStatefulCreatePages":false,"recordId":"rech4VeafLA2qBwkE","relatedRecords":[{"name":"Boise Code Camp - 2020","event_url":"http://boisecodecamp.com","location":"Boise State University","event_start_date":"2020-03-21","cfp_due_date":"2020-03-07","cfp_url":"https://sessionize.com/boisecodecamp-2020/","event_end_date":"2020-03-21","twitter":null,"perks_checked":true,"region":"Americas","subregion":"Northern America","icon":[{"url":"https://dl.airtable.com/.attachments/673fae32ad621a0c61f13946c2a438a3/cc5e9b8e/boisecodecamp.com"}],"country":"United States","created_date":"2020-02-03T20:20:44.000Z","created_days_back":161,"cfp_days_until":-129,"is_new":0,"description":"Boise Code Camp is Boise’s premier free-to-the-community software development technical event and the longest running Code Camp in the Northwest.","travel_covered":null,"hotel_covered":null,"stipend_covered":null,"record_id":"recsuWmOnN7yMbapr","category":[{"id":"17bb4611-8120-5f31-9bd1-7eabfa555d30","data":{"name":"General","description":"Conferences covering a wide range of web development and software engineering topics."},"fields":{"slug":"conferences/general"}}],"score":10},{"name":"Clearwater Development Conference 2020","event_url":"https://clearwater-analytics.com/devcon2020","location":"Boise, ID","event_start_date":"2020-10-23","cfp_due_date":"2020-07-22","cfp_url":"https://papercall.io/cfps/3230/submissions/new","event_end_date":"2020-10-23","twitter":null,"perks_checked":true,"region":"Americas","subregion":"Northern America","icon":[{"url":"https://dl.airtable.com/.attachments/3908ff445745d9c82b74d27ba64c9e04/dadaa345/clearwater-analytics.com"}],"country":"United States","created_date":"2020-06-24T04:20:24.000Z","created_days_back":20,"cfp_days_until":7,"is_new":0,"description":"One day educational conference focused on development, hosted by Clearwater Analytics.","travel_covered":true,"hotel_covered":true,"stipend_covered":null,"record_id":"recmHyPNJcLTqRUad","category":[{"id":"17bb4611-8120-5f31-9bd1-7eabfa555d30","data":{"name":"General","description":"Conferences covering a wide range of web development and software engineering topics."},"fields":{"slug":"conferences/general"}}],"score":10},{"name":"TEDxGrandJunction - 2020","event_url":"https://www.tedxgj.com","location":"Grand Junction, CO","event_start_date":"2020-03-07","cfp_due_date":"2019-11-25","cfp_url":"https://papercall.io/cfps/2584/submissions/new","event_end_date":"2020-03-07","twitter":null,"perks_checked":true,"region":"Americas","subregion":"Northern America","icon":[{"url":"https://dl.airtable.com/.attachments/4f0c543382008b6ac3a0a8406f47627d/ecf04ace/Logo-2-line-dark.jpg"}],"country":"United States","created_date":"2019-10-22T04:21:06.000Z","created_days_back":266,"cfp_days_until":-232,"is_new":0,"description":"Home","travel_covered":null,"hotel_covered":null,"stipend_covered":null,"record_id":"rechSvR6BKyrTZK9S","category":[{"id":"17bb4611-8120-5f31-9bd1-7eabfa555d30","data":{"name":"General","description":"Conferences covering a wide range of web development and software engineering topics."},"fields":{"slug":"conferences/general"}}],"score":10},{"name":"DeveloperWeek Global: Cloud","event_url":"https://www.developerweek.com/global/conference/cloud","location":"Online, Online","event_start_date":"2020-09-28","cfp_due_date":"2020-07-22","cfp_url":"https://www.developerweek.com/global/conference/cloud/apply-to-speak","event_end_date":"2020-09-29","twitter":"@developerweek","perks_checked":null,"region":"Americas","subregion":"Northern America","icon":[{"url":"https://dl.airtable.com/.attachments/ee46f61aea4fe45e675c65707c38692c/126bb663/developerweek.com"}],"country":"United States","created_date":"2020-07-13T15:20:37.000Z","created_days_back":0,"cfp_days_until":7,"is_new":1,"description":"-","travel_covered":null,"hotel_covered":null,"stipend_covered":null,"record_id":"recj4nHXLoCEFiQjC","category":[{"id":"17bb4611-8120-5f31-9bd1-7eabfa555d30","data":{"name":"General","description":"Conferences covering a wide range of web development and software engineering topics."},"fields":{"slug":"conferences/general"}}],"score":10}]}}