{"data":{"site":{"meta":{"title":"CFP Land","description":"Calls for Proposals, Tech Conferences, and Speaking Tips","url":"https://www.cfpland.com","author":"Karl L. Hughes","twitter":"cfp_land","image":"/img/default.png"}},"category":{"edges":[{"node":{"id":"3006c0c1-819e-5478-946a-37c2c2c98242","data":{"name":"Security","description":"Information and application security conferences."}}},{"node":{"id":"35643730-3914-5ccc-83d4-c02e76714995","data":{"name":"Ruby","description":"Ruby programming language conferences."}}},{"node":{"id":"2f707d71-008b-5aef-881e-eba8ae5fbcee","data":{"name":"Python","description":"Python programming language conferences."}}},{"node":{"id":"b86124ba-63b1-5c85-a83f-dafaadd02e57","data":{"name":"PHP","description":"PHP Hypertext Processor programming language conferences."}}},{"node":{"id":"d36479d7-0ddb-569f-9e50-e0e8e12759a6","data":{"name":"Mobile","description":"iOS and Android mobile design and development conferences."}}},{"node":{"id":"1d79004c-a91c-56b6-812c-a72fd277e65e","data":{"name":"Javascript","description":"Frontend and backend Javascript conferences."}}},{"node":{"id":"5397a316-d186-5896-9dca-24ef439e4dd7","data":{"name":"Java","description":"Java programming language conferences."}}},{"node":{"id":"c89af0ba-bd5f-5eb3-9ad2-b5f84ca83660","data":{"name":"Go","description":"Go programming language conferences."}}},{"node":{"id":"17bb4611-8120-5f31-9bd1-7eabfa555d30","data":{"name":"General","description":"Conferences covering a wide range of web development and software engineering topics."}}},{"node":{"id":"3db9c63a-a3f0-5e6d-87a8-13219235bfbb","data":{"name":"DevOps","description":"Developer Operations centered conferences."}}},{"node":{"id":"ab16d82c-a2b5-5f0c-9093-aca2d32617e0","data":{"name":"Design","description":"Design, user interface, and user experience conferences."}}},{"node":{"id":"fdc441fe-c4ba-5a1c-945c-b23eff87414b","data":{"name":"Data","description":"Machine learning, AI, Databases, and Big Data conferences."}}},{"node":{"id":"646eee51-7fa9-565e-ad12-047b1fd04b91","data":{"name":"CSS","description":"CSS stylesheet language conferences."}}},{"node":{"id":"526da865-5b6e-524b-942e-240033174fda","data":{"name":".NET","description":".NET and C# programming language conferences."}}}]},"conferences":{"edges":[{"node":{"id":"9d35e605-dbcc-5486-8e35-eff48fcf2393","data":{"name":"Virtual Symposium - Applied Data Science","event_url":"https://www.dataplatformgeeks.com","location":"Online","event_start_date":"2021-06-02","cfp_due_date":"2021-04-23","cfp_url":"https://sessionize.com/virtual-symposium-applied-data-science-june-2021/","event_end_date":"2021-06-02","twitter":null,"perks_checked":null,"region":"Americas","subregion":"Northern America","icon":[{"url":"https://dl.airtable.com/.attachments/4f1ab4a782e941ca869f989fddb93c88/22813e48/dataplatformgeeks.com"}],"city":"Alice","country":"United States","created_date":"2021-04-12T05:21:20.000Z","created_days_back":10,"cfp_days_until":0,"is_new":0,"description":"Welcome to DataPlatformGeeks. A community initiative by eDominer (an incarnation of SQLServerGeeks) is a community of Data & Analytics professionals.","travel_covered":null,"hotel_covered":null,"stipend_covered":null,"record_id":"recW8livLxUQPJGMB","category":[{"id":"fdc441fe-c4ba-5a1c-945c-b23eff87414b","data":{"name":"Data","description":"Machine learning, AI, Databases, and Big Data conferences."},"fields":{"slug":"conferences/data"}}]}}},{"node":{"id":"a1173502-1f41-57c6-8457-8ab1329d1816","data":{"name":"Code PaLOUsa 2021","event_url":"https://www.codepalousa.com","location":"Online","event_start_date":"2021-08-18","cfp_due_date":"2021-04-23","cfp_url":"https://sessionize.com/cpl21/","event_end_date":"2021-08-18","twitter":null,"perks_checked":null,"region":"Americas","subregion":"Northern America","icon":[{"url":"https://dl.airtable.com/.attachments/1819b2c5bed97b0f811183b77ca63fc1/b66986a4/codepalousa.com"}],"city":"Alice","country":"United States","created_date":"2021-03-31T04:20:36.000Z","created_days_back":22,"cfp_days_until":0,"is_new":0,"description":"Code PaLOUsa 2020","travel_covered":null,"hotel_covered":null,"stipend_covered":null,"record_id":"recxkjms6cpebM1Sh","category":[{"id":"17bb4611-8120-5f31-9bd1-7eabfa555d30","data":{"name":"General","description":"Conferences covering a wide range of web development and software engineering topics."},"fields":{"slug":"conferences/general"}}]}}},{"node":{"id":"772acb5c-42ae-5bdb-92c7-0fe11ca260bc","data":{"name":"N.O.W. Network of Women in IT","event_url":"https://www.linkedin.com/signup/cold-join","location":"Online","event_start_date":"2021-05-11","cfp_due_date":"2021-04-23","cfp_url":"https://sessionize.com/n-o-w--network-of-women-in-it/","event_end_date":"2021-05-11","twitter":null,"perks_checked":null,"region":"Americas","subregion":"Northern America","icon":[{"url":"https://dl.airtable.com/.attachments/5f58f330f23e519ff34d9c8ae099836c/0777528c/linkedin.com"}],"city":"Alice","country":"United States","created_date":"2021-03-25T04:20:29.000Z","created_days_back":28,"cfp_days_until":0,"is_new":0,"description":"500 million+ members | Manage your professional identity. Build and engage with your professional network. Access knowledge, insights and opportunities.","travel_covered":null,"hotel_covered":null,"stipend_covered":null,"record_id":"recmdKtFgRaPOjJAK","category":[{"id":"17bb4611-8120-5f31-9bd1-7eabfa555d30","data":{"name":"General","description":"Conferences covering a wide range of web development and software engineering topics."},"fields":{"slug":"conferences/general"}}]}}},{"node":{"id":"08e07fcc-4fcb-5eb7-ad40-f47197d373c5","data":{"name":"DevOps Connect: DevSecOps at RSA 2021","event_url":"https://www.mediaopsevents.com/virtual/upcoming","location":"Online","event_start_date":"2021-05-19","cfp_due_date":"2021-04-23","cfp_url":"https://sessionize.com/devsecops-rsa-2021/","event_end_date":"2021-05-19","twitter":null,"perks_checked":null,"region":"Americas","subregion":"Northern America","icon":[{"url":"https://dl.airtable.com/.attachments/b37cc118e24c083c45fa67de22710718/f0720a68/773437-5fbc423237f93.png"}],"city":"Alice","country":"United States","created_date":"2021-03-12T00:21:41.000Z","created_days_back":42,"cfp_days_until":0,"is_new":0,"description":"Upcoming Virtual Events","travel_covered":null,"hotel_covered":null,"stipend_covered":null,"record_id":"recuiozUb2DViBMg2","category":[{"id":"3db9c63a-a3f0-5e6d-87a8-13219235bfbb","data":{"name":"DevOps","description":"Developer Operations centered conferences."},"fields":{"slug":"conferences/devops"}}]}}},{"node":{"id":"c5287d25-0101-5ed7-8653-d06aea88408b","data":{"name":"Bizz Summit ES","event_url":"https://bizzsummit.es","location":"Online","event_start_date":"2021-06-04","cfp_due_date":"2021-04-24","cfp_url":"https://sessionize.com/bizz-summit-es/","event_end_date":"2021-06-04","twitter":null,"perks_checked":null,"region":"Americas","subregion":"Northern America","icon":[{"url":"https://dl.airtable.com/.attachments/169ad1c00bfd0e8864460d73d07a89a2/587bd76e/countdown_banner_large.jpg"}],"city":"Alice","country":"United States","created_date":"2021-03-13T00:20:22.000Z","created_days_back":41,"cfp_days_until":0,"is_new":0,"description":"-","travel_covered":null,"hotel_covered":null,"stipend_covered":null,"record_id":"reca2UkEzqDZ6h5kx","category":[{"id":"17bb4611-8120-5f31-9bd1-7eabfa555d30","data":{"name":"General","description":"Conferences covering a wide range of web development and software engineering topics."},"fields":{"slug":"conferences/general"}}]}}},{"node":{"id":"69c00d4d-6c37-591c-893e-72b0c295ae64","data":{"name":"Kafka Summit Americas 2021","event_url":"https://www.kafka-summit.org","location":"Online","event_start_date":"2021-09-14","cfp_due_date":"2021-04-25","cfp_url":"https://sessionize.com/kafka-summit-americas-2021/","event_end_date":"2021-09-14","twitter":null,"perks_checked":null,"region":"Americas","subregion":"Northern America","icon":[{"url":"https://dl.airtable.com/.attachments/6b9471078dfd7f732458988390f8d30d/6e22d553/icon-512x512.png"}],"city":"Alice","country":"United States","created_date":"2021-04-13T05:20:29.000Z","created_days_back":9,"cfp_days_until":1,"is_new":0,"description":"Real-time stream processing at massive scale","travel_covered":null,"hotel_covered":null,"stipend_covered":null,"record_id":"rec5azcKAQTJdkOW6","category":[{"id":"fdc441fe-c4ba-5a1c-945c-b23eff87414b","data":{"name":"Data","description":"Machine learning, AI, Databases, and Big Data conferences."},"fields":{"slug":"conferences/data"}}]}}},{"node":{"id":"2a594f2b-fc0a-5337-92bc-c2700305c1de","data":{"name":"nz.js(con); 2021","event_url":"https://conference.javascript.org.nz","location":"Wellington, New Zealand","event_start_date":"2021-06-21","cfp_due_date":"2021-04-25","cfp_url":"https://papercall.io/cfps/3636/submissions/new","event_end_date":"2021-06-22","twitter":null,"perks_checked":null,"region":"Oceania","subregion":"Australia and New Zealand","icon":[{"url":"https://dl.airtable.com/.attachments/bdf075658c3a8b6fa068cea03c2251f9/3787ef6d/icon-512x512.png"}],"city":"Wellington","country":"New Zealand","created_date":"2021-04-12T05:21:20.000Z","created_days_back":10,"cfp_days_until":1,"is_new":0,"description":"nz.js(con); 2021 website - NZ JavaScript conference","travel_covered":null,"hotel_covered":null,"stipend_covered":null,"record_id":"recCAr8myEyDFvPbS","category":[{"id":"1d79004c-a91c-56b6-812c-a72fd277e65e","data":{"name":"Javascript","description":"Frontend and backend Javascript conferences."},"fields":{"slug":"conferences/javascript"}}]}}},{"node":{"id":"d6767e6d-6ace-5347-9c8f-a4f4ece94ec1","data":{"name":"Data Saturday - Johannesburg","event_url":"https://www.eventbrite.com/e/data-saturday-johannesburg-2021-back-to-basics-tickets-134437071901","location":"Online","event_start_date":"2021-05-15","cfp_due_date":"2021-04-25","cfp_url":"https://sessionize.com/data-saturday-johannesburg/","event_end_date":"2021-05-15","twitter":null,"perks_checked":null,"region":"Americas","subregion":"Northern America","icon":[{"url":"https://dl.airtable.com/.attachments/753f16544a2a0d7de514dab44806f0e6/24e20c89/eventbrite.com"}],"city":"Alice","country":"United States","created_date":"2021-04-12T04:20:47.000Z","created_days_back":10,"cfp_days_until":1,"is_new":0,"description":"Data Saturday Johannesburg is a virtual online training event for professionals who use the Microsoft data platform.\nCommunity speakers w","travel_covered":null,"hotel_covered":null,"stipend_covered":null,"record_id":"recU7GnsiVLXxfl8X","category":[{"id":"fdc441fe-c4ba-5a1c-945c-b23eff87414b","data":{"name":"Data","description":"Machine learning, AI, Databases, and Big Data conferences."},"fields":{"slug":"conferences/data"}}]}}},{"node":{"id":"de744b26-732e-58d9-b3d3-d380efb66c58","data":{"name":"SPA Conference 2021","event_url":"https://www.spaconference.org","location":"Online","event_start_date":"2021-07-12","cfp_due_date":"2021-04-26","cfp_url":"https://sessionize.com/spa2021/","event_end_date":"2021-07-12","twitter":null,"perks_checked":null,"region":"Americas","subregion":"Northern America","icon":[{"url":"https://dl.airtable.com/.attachments/557555b7f3e9017e6273121398c8d448/953af4b6/spaconference.org"}],"city":"Alice","country":"United States","created_date":"2021-03-16T02:20:45.000Z","created_days_back":38,"cfp_days_until":2,"is_new":0,"description":"SPA Conference brings practitioners together to share latest thinking on best and emerging practices in software development.","travel_covered":null,"hotel_covered":null,"stipend_covered":null,"record_id":"reckDzrengKUpQFdo","category":[{"id":"1d79004c-a91c-56b6-812c-a72fd277e65e","data":{"name":"Javascript","description":"Frontend and backend Javascript conferences."},"fields":{"slug":"conferences/javascript"}}]}}},{"node":{"id":"f49f8285-e604-5c9c-8de5-4b10a272c7ed","data":{"name":"Virtual GitLab Commit 2021","event_url":"https://about.gitlab.com/events/commit/","location":"Virtual","event_start_date":"2021-08-03","cfp_due_date":"2021-04-30","cfp_url":"https://docs.google.com/forms/d/e/1FAIpQLSdYAnbBeMezbC_ZeqcTo31UHEKRhhem0wxEalM7Oy9KS3-j0w/viewform","event_end_date":null,"twitter":null,"perks_checked":null,"region":null,"subregion":null,"icon":[{"url":"https://dl.airtable.com/.attachments/82d8cb2844771ede1f3dd12576918d9f/9ee8f4c3/gitlab.com"}],"city":null,"country":null,"created_date":"2021-04-23T01:19:54.000Z","created_days_back":0,"cfp_days_until":6,"is_new":1,"description":"Join us and commit to a day of DevOps inspiration and innovation at GitLab Commit Virtual. Now accepting talk submissions!","travel_covered":null,"hotel_covered":null,"stipend_covered":null,"record_id":"recTJTvH2CRM09MBT","category":[{"id":"3db9c63a-a3f0-5e6d-87a8-13219235bfbb","data":{"name":"DevOps","description":"Developer Operations centered conferences."},"fields":{"slug":"conferences/devops"}}]}}},{"node":{"id":"c615c461-be24-54ba-aefc-5728575da507","data":{"name":"The IEEE Third International Conference On Artificial Intelligence Testing (AITest 2021)","event_url":"http://www.ieeeaitests.com/index.html","location":"Virtual","event_start_date":"2021-08-23","cfp_due_date":"2021-04-30","cfp_url":"http://www.ieeeaitests.com/html/callForPapers.html","event_end_date":null,"twitter":null,"perks_checked":null,"region":null,"subregion":null,"icon":[{"url":"https://dl.airtable.com/.attachments/d363999ad975779edb3a2d260df5f778/ab04579b/ai_logo.png"}],"city":null,"country":null,"created_date":"2021-04-22T02:41:18.000Z","created_days_back":1,"cfp_days_until":6,"is_new":1,"description":"The IEEE Third International Conference On Artificial Intelligence Testing (AITest 2020)","travel_covered":null,"hotel_covered":null,"stipend_covered":null,"record_id":"reczqQ0zwGVtC4CyK","category":[{"id":"2f707d71-008b-5aef-881e-eba8ae5fbcee","data":{"name":"Python","description":"Python programming language conferences."},"fields":{"slug":"conferences/python"}}]}}},{"node":{"id":"6e4c4cef-c872-50b8-9182-1f300a41e92e","data":{"name":"Code PaLOUsa 2021","event_url":"https://www.codepalousa.com","location":"Online","event_start_date":"2021-08-18","cfp_due_date":"2021-04-30","cfp_url":"https://sessionize.com/cpl21","event_end_date":null,"twitter":null,"perks_checked":null,"region":"Americas","subregion":"Northern America","icon":[{"url":"https://dl.airtable.com/.attachments/f28693b88efa24f006e1d45bd93ebedd/8b32d009/codepalousa.com"}],"city":"Alice","country":"United States","created_date":"2021-04-18T20:38:16.000Z","created_days_back":4,"cfp_days_until":6,"is_new":1,"description":"Code PaLOUsa 2021","travel_covered":null,"hotel_covered":null,"stipend_covered":null,"record_id":"recApaLjfSCJ3Q0wY","category":[{"id":"17bb4611-8120-5f31-9bd1-7eabfa555d30","data":{"name":"General","description":"Conferences covering a wide range of web development and software engineering topics."},"fields":{"slug":"conferences/general"}}]}}},{"node":{"id":"fa8ba5be-096f-5afa-ab23-0a939381410f","data":{"name":"DDD East Midlands Conference 2021","event_url":"https://www.dddeastmidlands.com","location":"Nottingham Conference Center, 30 Burton St, Nottingham NG1 4BU","event_start_date":"2021-10-02","cfp_due_date":"2021-04-30","cfp_url":"https://sessionize.com/ddd-east-midlands-conference-2021/","event_end_date":"2021-10-02","twitter":null,"perks_checked":null,"region":"Europe","subregion":"Northern Europe","icon":[{"url":"https://dl.airtable.com/.attachments/6d7e99c2c5946146ad2af40dbefe543c/4deed1f5/dddeastmidlands.com"}],"city":null,"country":"United Kingdom","created_date":"2021-04-03T04:20:20.000Z","created_days_back":19,"cfp_days_until":6,"is_new":0,"description":"A technology conference for the community, by the community. Celebrates the East Midlands tech community, businesses and talent have to offer through collaboration & innovation.","travel_covered":null,"hotel_covered":null,"stipend_covered":null,"record_id":"recfiBF36DX42Q8ap","category":[{"id":"17bb4611-8120-5f31-9bd1-7eabfa555d30","data":{"name":"General","description":"Conferences covering a wide range of web development and software engineering topics."},"fields":{"slug":"conferences/general"}}]}}},{"node":{"id":"ed7f0bf3-2985-586b-98b4-7083e325c007","data":{"name":"The Perl and Raku Conference 2021","event_url":"https://perlconference.us/tprc-2021-cloud","location":"The Cloud","event_start_date":"2021-06-08","cfp_due_date":"2021-04-30","cfp_url":"https://papercall.io/cfps/3753/submissions/new","event_end_date":"2021-06-08","twitter":null,"perks_checked":null,"region":null,"subregion":null,"icon":[{"url":"https://dl.airtable.com/.attachments/0436b17661edd07ad95568a1cf4fd0a1/d5131ccf/perlconference.us"}],"city":null,"country":"Online","created_date":"2021-04-02T04:20:48.000Z","created_days_back":20,"cfp_days_until":6,"is_new":0,"description":"COVID-19 has kept us all home. However, we still have great things to share about Perl and Raku. Join us for a 3-day event including interactive talks and forums.","travel_covered":null,"hotel_covered":null,"stipend_covered":null,"record_id":"recKIbZJizEW3rjyj","category":[{"id":"17bb4611-8120-5f31-9bd1-7eabfa555d30","data":{"name":"General","description":"Conferences covering a wide range of web development and software engineering topics."},"fields":{"slug":"conferences/general"}}]}}},{"node":{"id":"b455513d-fc9c-5ed6-a9e6-5be6f1cdbe97","data":{"name":"YallaDevOps 2021","event_url":"https://yalla-devops.com","location":"Tel aviv University","event_start_date":"2022-07-08","cfp_due_date":"2021-04-30","cfp_url":"https://sessionize.com/yalladevops-2021/","event_end_date":"2022-07-08","twitter":null,"perks_checked":null,"region":"Asia","subregion":"Western Asia","icon":[{"url":"https://dl.airtable.com/.attachments/9f323885096029c73a996d50559ad6cf/01567e12/jfrog-logo-300x290.png"}],"city":null,"country":"Israel","created_date":"2021-03-30T04:20:40.000Z","created_days_back":23,"cfp_days_until":6,"is_new":0,"description":"Join the DevOps conference exploring tools & ecosystems. Topics include: Cloud Native, K8S, CICD, DevSecOps, Go. Share & learn how to release software faster.","travel_covered":null,"hotel_covered":null,"stipend_covered":null,"record_id":"recfxNj0hxhOVEe6O","category":[{"id":"3db9c63a-a3f0-5e6d-87a8-13219235bfbb","data":{"name":"DevOps","description":"Developer Operations centered conferences."},"fields":{"slug":"conferences/devops"}}]}}},{"node":{"id":"1e9ac761-1dff-523d-9868-eeed696a27e5","data":{"name":"Alchemy Conf 2020","event_url":"https://alchemyconf.com","location":"Online","event_start_date":"2021-05-28","cfp_due_date":"2021-04-30","cfp_url":"https://papercall.io/cfps/3734/submissions/new","event_end_date":"2021-05-28","twitter":null,"perks_checked":null,"region":"Americas","subregion":"Northern America","icon":[{"url":"https://dl.airtable.com/.attachments/cb101e9264bd4add6bb7a4212403b878/20582f1f/favicon.png"}],"city":"Alice","country":"United States","created_date":"2021-03-27T04:20:34.000Z","created_days_back":26,"cfp_days_until":6,"is_new":0,"description":"The most exquisite Elixir conference in Portugal.","travel_covered":null,"hotel_covered":null,"stipend_covered":null,"record_id":"recoELZmoW7CYdblV","category":[{"id":"17bb4611-8120-5f31-9bd1-7eabfa555d30","data":{"name":"General","description":"Conferences covering a wide range of web development and software engineering topics."},"fields":{"slug":"conferences/general"}}]}}},{"node":{"id":"0736eb9a-c0e0-56f1-9ffd-bdd1c5e5b437","data":{"name":"SQL Start! 2021","event_url":"https://www.sqlstart.it/2021","location":"Online","event_start_date":"2021-06-11","cfp_due_date":"2021-04-30","cfp_url":"https://sessionize.com/sql-start-2021/","event_end_date":"2021-06-11","twitter":null,"perks_checked":null,"region":"Americas","subregion":"Northern America","icon":[{"url":"https://dl.airtable.com/.attachments/23977fa56add48d0ce70fb7569770cf1/0129ae67/top-1.jpg"}],"city":"Alice","country":"United States","created_date":"2021-03-26T04:21:00.000Z","created_days_back":27,"cfp_days_until":6,"is_new":0,"description":"SQL Start! 2021 è la tua opportunità per incontrare i maggiori esperti della Microsoft Data Platform e confrontarti sulle tematiche ad essa collegate in una giornata formativa ad altissimo valore aggiunto.","travel_covered":null,"hotel_covered":null,"stipend_covered":null,"record_id":"recwlZTp476Fmxs3I","category":[{"id":"fdc441fe-c4ba-5a1c-945c-b23eff87414b","data":{"name":"Data","description":"Machine learning, AI, Databases, and Big Data conferences."},"fields":{"slug":"conferences/data"}}]}}},{"node":{"id":"4ebabacc-1d62-5181-be9f-74bbb39b695e","data":{"name":"Ignite Summit","event_url":"https://ignite-summit.org/","location":"Online","event_start_date":"2021-05-25","cfp_due_date":"2021-04-30","cfp_url":"https://sessionize.com/ignite-summit","event_end_date":null,"twitter":null,"perks_checked":null,"region":"Americas","subregion":"Northern America","icon":[{"url":"https://dl.airtable.com/.attachments/5d4feb1890d65fa7a02d9a9051dea70c/70814519/icon-512x512.png"}],"city":"Alice","country":"United States","created_date":"2021-03-25T11:51:00.000Z","created_days_back":28,"cfp_days_until":6,"is_new":0,"description":"A conference for developers who use Apache Ignite, by developers who built Apache Ignite.","travel_covered":null,"hotel_covered":null,"stipend_covered":null,"record_id":"recmKOJn4GLXMuhWZ","category":[{"id":"5397a316-d186-5896-9dca-24ef439e4dd7","data":{"name":"Java","description":"Java programming language conferences."},"fields":{"slug":"conferences/java"}}]}}},{"node":{"id":"36ec84db-2e10-532a-884f-85e64021d59d","data":{"name":"SQL Start! 2021","event_url":"https://www.sqlstart.it/2020","location":"Online","event_start_date":"2021-06-11","cfp_due_date":"2021-04-30","cfp_url":"https://sessionize.com/sql-start-2021/","event_end_date":"2021-06-11","twitter":null,"perks_checked":null,"region":"Americas","subregion":"Northern America","icon":[{"url":"https://dl.airtable.com/.attachments/20d3ad3e81adb7801227424505bb4cdd/e3e9157f/top-1.jpg"}],"city":"Alice","country":"United States","created_date":"2021-03-21T04:21:14.000Z","created_days_back":32,"cfp_days_until":6,"is_new":0,"description":"Gli speaker di SQL Start! sono tra i migliori esperti del settore, con una lunga esperienza sul campo sulle tecnologie Microsoft, non solo teorica.","travel_covered":null,"hotel_covered":null,"stipend_covered":null,"record_id":"recqQAtYif6oLcEwH","category":[{"id":"fdc441fe-c4ba-5a1c-945c-b23eff87414b","data":{"name":"Data","description":"Machine learning, AI, Databases, and Big Data conferences."},"fields":{"slug":"conferences/data"}}]}}},{"node":{"id":"945732fd-5b2d-55f5-856a-2ae0e3d72e16","data":{"name":"June Microsoft 365 Collaboration Conference","event_url":"https://m365conf.com","location":"Walt Disney World Swan","event_start_date":"2021-06-08","cfp_due_date":"2021-04-30","cfp_url":"https://sessionize.com/junem356conf/","event_end_date":"2021-06-08","twitter":null,"perks_checked":null,"region":"Americas","subregion":"Northern America","icon":[{"url":"https://dl.airtable.com/.attachments/0f637689409b8fe8c9af595a214a9304/1c8b6e6b/m365conf.com"}],"city":null,"country":"United States","created_date":"2021-03-19T00:20:31.000Z","created_days_back":35,"cfp_days_until":6,"is_new":0,"description":"Microsoft 365 Collaboration Conference is a premier opportunity to hear experts from Microsoft and around the world share their experience and knowledge about a variety of topics such as cloud services, best practices & real world project insights.","travel_covered":null,"hotel_covered":null,"stipend_covered":null,"record_id":"recvwnTX7deQfMCVe","category":[{"id":"17bb4611-8120-5f31-9bd1-7eabfa555d30","data":{"name":"General","description":"Conferences covering a wide range of web development and software engineering topics."},"fields":{"slug":"conferences/general"}}]}}},{"node":{"id":"5f777be9-23d6-5bf4-aef8-6006e33f7a11","data":{"name":"Subsurface LIVE Summer 2021","event_url":"https://subsurfaceconf.com/Summer2021/info","location":"Online","event_start_date":"2021-07-21","cfp_due_date":"2021-04-30","cfp_url":"https://sessionize.com/subsurface-live-summer-2021/","event_end_date":"2021-07-21","twitter":null,"perks_checked":null,"region":"Americas","subregion":"Northern America","icon":[{"url":"https://dl.airtable.com/.attachments/22231ef9d013155f1618cc49ea0b296e/559d6b97/subsurfaceconf.com"}],"city":"Alice","country":"United States","created_date":"2021-03-19T00:20:31.000Z","created_days_back":35,"cfp_days_until":6,"is_new":0,"description":"-","travel_covered":null,"hotel_covered":null,"stipend_covered":null,"record_id":"recvq65KqOWzh045C","category":[{"id":"17bb4611-8120-5f31-9bd1-7eabfa555d30","data":{"name":"General","description":"Conferences covering a wide range of web development and software engineering topics."},"fields":{"slug":"conferences/general"}}]}}},{"node":{"id":"4d943648-5ede-5dca-b1ac-d7887f2fe0ad","data":{"name":"ContainerDays 2021","event_url":"https://www.containerdays.io","location":"Hamburg, Germany","event_start_date":"2021-07-06","cfp_due_date":"2021-04-30","cfp_url":"https://sessionize.com/containerdays-2021/","event_end_date":"2021-07-06","twitter":null,"perks_checked":null,"region":"Europe","subregion":"Western Europe","icon":[{"url":"https://dl.airtable.com/.attachments/e13d78d837ab203a0f065d767b0393a8/8710729a/containerdays.io"}],"city":"Hamburg","country":"Germany","created_date":"2021-03-19T00:20:31.000Z","created_days_back":35,"cfp_days_until":6,"is_new":0,"description":"We are currently planning the next edition of ContainerDays in 2021. Further information will follow soon. Stay safe and healthy!","travel_covered":null,"hotel_covered":null,"stipend_covered":null,"record_id":"recsBrfnDLE59yR4v","category":[{"id":"3db9c63a-a3f0-5e6d-87a8-13219235bfbb","data":{"name":"DevOps","description":"Developer Operations centered conferences."},"fields":{"slug":"conferences/devops"}}]}}},{"node":{"id":"223eb3cc-b2ee-5752-9bd2-8f610f9f9395","data":{"name":"BlazorDay 2021","event_url":"https://blazorday.net","location":"Online","event_start_date":"2021-06-17","cfp_due_date":"2021-04-30","cfp_url":"https://sessionize.com/blazorday-2021/","event_end_date":"2021-06-17","twitter":null,"perks_checked":null,"region":"Americas","subregion":"Northern America","icon":[{"url":"https://dl.airtable.com/.attachments/1e660efb02f5dea7bebe0541e133cf57/d18181ca/favicon-192.png"}],"city":"Alice","country":"United States","created_date":"2021-03-19T00:20:31.000Z","created_days_back":35,"cfp_days_until":6,"is_new":0,"description":"After more than 10K live viewers, the second edition of the BlazorDay comes back. With more Blazor rock stars, more fun and more ... Blazor.","travel_covered":null,"hotel_covered":null,"stipend_covered":null,"record_id":"recV14SSCw8vGmnzW","category":[{"id":"526da865-5b6e-524b-942e-240033174fda","data":{"name":".NET","description":".NET and C# programming language conferences."},"fields":{"slug":"conferences/.net"}}]}}},{"node":{"id":"79692674-4296-5b17-b12d-cdc54f693920","data":{"name":"REVULN 21 Manila","event_url":"https://revuln.com/21manila.htm","location":"RED Hotel Cubao","event_start_date":"2021-05-20","cfp_due_date":"2021-04-30","cfp_url":"https://sessionize.com/revuln21manila/","event_end_date":"2021-05-20","twitter":null,"perks_checked":null,"region":"Asia","subregion":"South-Eastern Asia","icon":[{"url":"https://dl.airtable.com/.attachments/ca82e540db09fb85cca0ff8e8bfd9a62/89f18749/revuln.com"}],"city":null,"country":"Philippines","created_date":"2021-03-19T00:20:31.000Z","created_days_back":35,"cfp_days_until":6,"is_new":0,"description":"REVULN 21 Manila, 20-22 May 2021 - Cybersecurity communities","travel_covered":null,"hotel_covered":null,"stipend_covered":null,"record_id":"recUOJFCSxaBiewcx","category":[{"id":"3006c0c1-819e-5478-946a-37c2c2c98242","data":{"name":"Security","description":"Information and application security conferences."},"fields":{"slug":"conferences/security"}}]}}},{"node":{"id":"85c3c459-e759-5c2b-82ce-ae81d09f7741","data":{"name":"JCON 2021","event_url":"https://jcon.one/en","location":"Online","event_start_date":"2021-10-05","cfp_due_date":"2021-04-30","cfp_url":"https://sessionize.com/jcon-2021/","event_end_date":"2021-10-05","twitter":null,"perks_checked":null,"region":"Americas","subregion":"Northern America","icon":[{"url":"https://dl.airtable.com/.attachments/5dc6f6861cb785c3efbc0720bfe533a9/a5255e8e/jcon.one"}],"city":"Alice","country":"United States","created_date":"2021-03-19T00:20:31.000Z","created_days_back":35,"cfp_days_until":6,"is_new":0,"description":"JCON-ONLINE 2020 - Die große Java Community Konferenz - Oktober 27-30, 2020","travel_covered":null,"hotel_covered":null,"stipend_covered":null,"record_id":"recSwitnej1WZlzA6","category":[{"id":"5397a316-d186-5896-9dca-24ef439e4dd7","data":{"name":"Java","description":"Java programming language conferences."},"fields":{"slug":"conferences/java"}}]}}},{"node":{"id":"5ec53e9f-7daa-54c8-af0b-145da21e3ba7","data":{"name":"Ignite Summit","event_url":"https://ignite-summit.org","location":"Online","event_start_date":"2021-05-25","cfp_due_date":"2021-04-30","cfp_url":"https://sessionize.com/ignite-summit/","event_end_date":"2021-05-25","twitter":null,"perks_checked":null,"region":"Americas","subregion":"Northern America","icon":[{"url":"https://dl.airtable.com/.attachments/44d6db70918f2643f5cc5f5accb1d63a/73b6437f/icon-512x512.png"}],"city":"Alice","country":"United States","created_date":"2021-03-18T23:20:41.000Z","created_days_back":35,"cfp_days_until":6,"is_new":0,"description":"A conference for developers who use Apache Ignite, by developers who built Apache Ignite.","travel_covered":null,"hotel_covered":null,"stipend_covered":null,"record_id":"rec0zM5Djt3aA2k4v","category":[{"id":"17bb4611-8120-5f31-9bd1-7eabfa555d30","data":{"name":"General","description":"Conferences covering a wide range of web development and software engineering topics."},"fields":{"slug":"conferences/general"}}]}}},{"node":{"id":"afba63f8-f20c-5ac8-82d0-6706d7565a3f","data":{"name":"M365 Philly Virtual 2021","event_url":"https://www.spsevents.org/event/sharepoint-saturday-philly","location":"Online","event_start_date":"2021-05-14","cfp_due_date":"2021-04-30","cfp_url":"https://sessionize.com/m365-philly-2021/","event_end_date":"2021-05-14","twitter":null,"perks_checked":null,"region":"Americas","subregion":"Northern America","icon":[{"url":"https://dl.airtable.com/.attachments/954d1f9711cdcebb13fa3122e40eb95b/e4291b00/spsevents.org"}],"city":"Alice","country":"United States","created_date":"2021-03-18T00:21:30.000Z","created_days_back":36,"cfp_days_until":6,"is_new":0,"description":"We’re back and this year’s event will be virtual!","travel_covered":null,"hotel_covered":null,"stipend_covered":null,"record_id":"reciK7UEwIJSt8icy","category":[{"id":"17bb4611-8120-5f31-9bd1-7eabfa555d30","data":{"name":"General","description":"Conferences covering a wide range of web development and software engineering topics."},"fields":{"slug":"conferences/general"}}]}}},{"node":{"id":"061663d4-a906-5226-9179-13c8ab2e6a11","data":{"name":"DevFest Live","event_url":"https://devfest.live","location":"Online","event_start_date":"2021-05-22","cfp_due_date":"2021-04-30","cfp_url":"https://sessionize.com/devfest-live/","event_end_date":"2021-05-22","twitter":null,"perks_checked":null,"region":"Americas","subregion":"Northern America","icon":[{"url":"https://dl.airtable.com/.attachments/4c0acc68914dc8375999bd80eed14520/0efb0f42/icon-192.png"}],"city":"Alice","country":"United States","created_date":"2021-03-18T00:21:30.000Z","created_days_back":36,"cfp_days_until":6,"is_new":0,"description":"Join the community, learn new things!","travel_covered":null,"hotel_covered":null,"stipend_covered":null,"record_id":"recf0r6w4nhZrz3JQ","category":[{"id":"17bb4611-8120-5f31-9bd1-7eabfa555d30","data":{"name":"General","description":"Conferences covering a wide range of web development and software engineering topics."},"fields":{"slug":"conferences/general"}}]}}},{"node":{"id":"69813e22-996c-5b2e-8987-e67e70ffa70c","data":{"name":"Construction in the 21st Century 12th International Conference (CITC-12)","event_url":"https://www.citcglobal.com/","location":"Al-Zaytoona University Campus, Amman, Jordan","event_start_date":"2021-10-11","cfp_due_date":"2021-04-30","cfp_url":"https://www.citcglobal.com/cfp","event_end_date":null,"twitter":null,"perks_checked":null,"region":"Asia","subregion":"Western Asia","icon":[{"url":"https://dl.airtable.com/.attachments/05b3f831327917a5ce7fd12960f6bafd/749ef37e/0d72f4_234400117ab2469fb6b76f9e8de6bebef000.webp"}],"city":null,"country":"Jordan","created_date":"2021-02-11T15:43:42.000Z","created_days_back":70,"cfp_days_until":6,"is_new":0,"description":"International construction management and architecture conference in London, UK, September 9-11, 2019, hosted by East Carolina University, U.S.A.","travel_covered":null,"hotel_covered":null,"stipend_covered":null,"record_id":"recsDnTFLIOSHXqMM","category":[{"id":"ab16d82c-a2b5-5f0c-9093-aca2d32617e0","data":{"name":"Design","description":"Design, user interface, and user experience conferences."},"fields":{"slug":"conferences/design"}}]}}},{"node":{"id":"f785e682-a4dd-5174-ad0c-61df17f5978b","data":{"name":"IEEE Big Data Service 2021","event_url":"http://www.big-dataservice.net/","location":"Virtual","event_start_date":"2021-08-23","cfp_due_date":"2021-05-01","cfp_url":"http://www.big-dataservice.net/#callForPaper","event_end_date":null,"twitter":null,"perks_checked":null,"region":null,"subregion":null,"icon":[{"url":"https://dl.airtable.com/.attachments/037db7f87475d61464be37a6a41ce9bb/fa6cb527/bigDataLogo.png"}],"city":null,"country":null,"created_date":"2021-04-22T07:01:44.000Z","created_days_back":0,"cfp_days_until":7,"is_new":1,"description":"The Fifth IEEE International Conference On Big Data Service And Applications (IEEE Big Data Service 2021) will be held in San Francisco, California on April 4 – 9. 2019","travel_covered":null,"hotel_covered":null,"stipend_covered":null,"record_id":"recosjE5QyeGYQUqW","category":[{"id":"fdc441fe-c4ba-5a1c-945c-b23eff87414b","data":{"name":"Data","description":"Machine learning, AI, Databases, and Big Data conferences."},"fields":{"slug":"conferences/data"}}]}}},{"node":{"id":"d5649202-975f-566c-bfa5-6824e24837cd","data":{"name":"IEEE Mobile Cloud 2021","event_url":"https://www.mobile-cloud.net/","location":"Virtual","event_start_date":"2021-08-23","cfp_due_date":"2021-05-01","cfp_url":"https://www.mobile-cloud.net/#call-for-papers","event_end_date":null,"twitter":null,"perks_checked":null,"region":null,"subregion":null,"icon":[{"url":"https://dl.airtable.com/.attachments/678c5c9c0abadc73610fa8848ca26484/01d34deb/ieeelogos.png"}],"city":null,"country":null,"created_date":"2021-04-22T07:00:11.000Z","created_days_back":0,"cfp_days_until":7,"is_new":1,"description":"The 9th IEEE International Conference on Mobile Cloud Computing, Services, and Engineering (Mobile Cloud 2021) will be held virtual online on August 23-26. 2021","travel_covered":null,"hotel_covered":null,"stipend_covered":null,"record_id":"recVzPI8LsBcV4pL8","category":[{"id":"fdc441fe-c4ba-5a1c-945c-b23eff87414b","data":{"name":"Data","description":"Machine learning, AI, Databases, and Big Data conferences."},"fields":{"slug":"conferences/data"}}]}}},{"node":{"id":"09df30fb-9ee1-533a-b5c5-05259bcd83d9","data":{"name":"GeekBeacon Fest","event_url":"https://www.gbfest.org","location":"Online","event_start_date":"2021-10-15","cfp_due_date":"2021-05-01","cfp_url":"https://sessionize.com/gbfest/","event_end_date":"2021-10-15","twitter":null,"perks_checked":null,"region":"Americas","subregion":"Northern America","icon":[{"url":"https://dl.airtable.com/.attachments/e9bfe1bc706204b4b94b0875ab594aa3/adfb8b9a/gbf_www_banner_v2-2.jpg"}],"city":"Alice","country":"United States","created_date":"2021-03-20T00:21:07.000Z","created_days_back":34,"cfp_days_until":7,"is_new":0,"description":"GeekBeacon Fest’s mission is to unify geeks and make the world a better place though a celebration of Mental Health, Gaming, Open Culture, and Open Source.","travel_covered":null,"hotel_covered":null,"stipend_covered":null,"record_id":"recCO9IlnigNgzqz2","category":[{"id":"17bb4611-8120-5f31-9bd1-7eabfa555d30","data":{"name":"General","description":"Conferences covering a wide range of web development and software engineering topics."},"fields":{"slug":"conferences/general"}}]}}},{"node":{"id":"7e3e9694-bc34-55fe-b2ea-fe3351147aba","data":{"name":"Agi&#39;Lille 2020","event_url":"https://agilille.fr","location":"Online","event_start_date":"2020-06-25","cfp_due_date":"2021-05-01","cfp_url":"https://sessionize.com/agilille-2021/","event_end_date":"2020-06-25","twitter":null,"perks_checked":null,"region":"Americas","subregion":"Northern America","icon":null,"city":"Alice","country":"United States","created_date":"2021-03-20T00:21:06.000Z","created_days_back":34,"cfp_days_until":7,"is_new":0,"description":null,"travel_covered":null,"hotel_covered":null,"stipend_covered":null,"record_id":"recwOn4tcNjT4Nfjl","category":[{"id":"17bb4611-8120-5f31-9bd1-7eabfa555d30","data":{"name":"General","description":"Conferences covering a wide range of web development and software engineering topics."},"fields":{"slug":"conferences/general"}}]}}},{"node":{"id":"13974815-1b32-54f3-b36e-e2e55334e344","data":{"name":"Experts Live Austria 2021-2","event_url":"http://www.expertslive.at","location":"Linz, Upper Austria, Austria","event_start_date":"2021-06-25","cfp_due_date":"2021-05-02","cfp_url":"https://sessionize.com/experts-live-austria-2021-2/","event_end_date":"2021-06-25","twitter":null,"perks_checked":null,"region":"Europe","subregion":"Western Europe","icon":[{"url":"https://dl.airtable.com/.attachments/8876ace1f497f156b716ce32662e2f01/83cbf449/expertslive.at"}],"city":"Linz","country":"Austria","created_date":"2021-03-31T04:20:36.000Z","created_days_back":22,"cfp_days_until":8,"is_new":0,"description":"Das war das","travel_covered":null,"hotel_covered":null,"stipend_covered":null,"record_id":"recvkNT4GdGizN9Cs","category":[{"id":"17bb4611-8120-5f31-9bd1-7eabfa555d30","data":{"name":"General","description":"Conferences covering a wide range of web development and software engineering topics."},"fields":{"slug":"conferences/general"}}]}}},{"node":{"id":"075bc56e-324e-5864-938d-5c6fe9a7ecfc","data":{"name":"Hack In Paris 2021","event_url":"https://hackinparis.com","location":"Online","event_start_date":"2021-11-18","cfp_due_date":"2021-05-03","cfp_url":"https://papercall.io/cfps/3759/submissions/new","event_end_date":"2021-11-19","twitter":null,"perks_checked":null,"region":"Americas","subregion":"Northern America","icon":[{"url":"https://dl.airtable.com/.attachments/2b3aba0a4b2f9f01df204b0747f7d4cb/da57cfdd/hackinparis.com"}],"city":"Alice","country":"United States","created_date":"2021-04-14T04:21:30.000Z","created_days_back":8,"cfp_days_until":9,"is_new":0,"description":"Hack In Paris, the IT security event, will be held for the ninth time in France, at the La Maison de la Chimie. Hack In\nParis attendees will discover the realities of hacking, and its consequences for companies by offering 3 days- trainings\nand 2 days-conferences.","travel_covered":null,"hotel_covered":null,"stipend_covered":null,"record_id":"recu8oXFTsLP92YnI","category":[{"id":"17bb4611-8120-5f31-9bd1-7eabfa555d30","data":{"name":"General","description":"Conferences covering a wide range of web development and software engineering topics."},"fields":{"slug":"conferences/general"}}]}}},{"node":{"id":"f73a91ea-437f-5203-a8ef-1ab3e78f7d70","data":{"name":"eOne Event","event_url":"https://www.eonesolutions.com/event2021","location":"Online","event_start_date":"2021-09-01","cfp_due_date":"2021-05-03","cfp_url":"https://sessionize.com/eone-event2021/","event_end_date":"2021-09-01","twitter":null,"perks_checked":null,"region":"Americas","subregion":"Northern America","icon":[{"url":"https://dl.airtable.com/.attachments/b64ddeccca46cd1a3a8f658b8a63c61d/7bcede00/eonesolutions.com"}],"city":"Alice","country":"United States","created_date":"2021-03-22T00:20:45.000Z","created_days_back":32,"cfp_days_until":9,"is_new":0,"description":"Join us for eOne’s first ever virtual event designed with education in mind for our users to be empowered for success by the all the possibilities.","travel_covered":null,"hotel_covered":null,"stipend_covered":null,"record_id":"recFpMBhLC3DFnOHi","category":[{"id":"17bb4611-8120-5f31-9bd1-7eabfa555d30","data":{"name":"General","description":"Conferences covering a wide range of web development and software engineering topics."},"fields":{"slug":"conferences/general"}}]}}},{"node":{"id":"cd7f64ef-0a3d-5772-8906-7b129bceb99c","data":{"name":"DevopsDays Medellin 2021","event_url":"https://devopsdays.org/events/2021-medellin/welcome","location":"Medellin, Colombia","event_start_date":"2021-07-30","cfp_due_date":"2021-05-03","cfp_url":"https://papercall.io/cfps/3037/submissions/new","event_end_date":"2021-07-31","twitter":null,"perks_checked":null,"region":"Americas","subregion":"South America","icon":[{"url":"https://dl.airtable.com/.attachments/33c11a0c5906173073b5cc7854a9807f/91f771bf/devopsdays.org"}],"city":"Medellín","country":"Colombia","created_date":"2021-03-21T13:21:06.000Z","created_days_back":32,"cfp_days_until":9,"is_new":0,"description":"Welcome to DevOpsDays Medellín 2021","travel_covered":null,"hotel_covered":null,"stipend_covered":null,"record_id":"recPieydFy1kVj4La","category":[{"id":"3db9c63a-a3f0-5e6d-87a8-13219235bfbb","data":{"name":"DevOps","description":"Developer Operations centered conferences."},"fields":{"slug":"conferences/devops"}}]}}},{"node":{"id":"b0750ee1-542a-5310-9476-31a25ff1388b","data":{"name":"Upstream 2021","event_url":"https://upstream.live","location":"Virtual","event_start_date":"2021-06-07","cfp_due_date":"2021-05-04","cfp_url":"https://papercall.io/cfps/3743/submissions/new","event_end_date":"2021-06-07","twitter":null,"perks_checked":null,"region":null,"subregion":null,"icon":[{"url":"https://dl.airtable.com/.attachments/1fa4dbecc9aaf84fc19ca6f80caf7fc4/94d592fb/favicon-32x32.png"}],"city":null,"country":"Online","created_date":"2021-04-07T04:20:39.000Z","created_days_back":15,"cfp_days_until":10,"is_new":0,"description":"Join us on June 7th for Upstream 2021, a free event celebrating open source, the developers who use it and the maintainers who create it!","travel_covered":null,"hotel_covered":null,"stipend_covered":null,"record_id":"recLAOXvU26A6hKfp","category":[{"id":"17bb4611-8120-5f31-9bd1-7eabfa555d30","data":{"name":"General","description":"Conferences covering a wide range of web development and software engineering topics."},"fields":{"slug":"conferences/general"}}]}}},{"node":{"id":"c13212aa-50ba-5d90-9738-26cdbbf157b3","data":{"name":"ScotlandPHP 2021","event_url":"https://conference.scotlandphp.co.uk/2021/","location":"Edinburgh, UK","event_start_date":"2021-10-22","cfp_due_date":"2021-05-04","cfp_url":"https://cfs.scotlandphp.co.uk/","event_end_date":null,"twitter":null,"perks_checked":null,"region":"Europe","subregion":"Northern Europe","icon":[{"url":"https://dl.airtable.com/.attachments/249b15cf8e95e3d2ce704d2b71a6bc4d/b3455aa5/scotlandphp.co.uk"}],"city":"Edinburgh","country":"United Kingdom","created_date":"2021-03-30T20:05:01.000Z","created_days_back":23,"cfp_days_until":10,"is_new":0,"description":"We’re finally back for the 5th edition! Sign up to stay up to date with all the latest conference news.","travel_covered":null,"hotel_covered":null,"stipend_covered":null,"record_id":"rectlGElTExrUxoDy","category":[{"id":"b86124ba-63b1-5c85-a83f-dafaadd02e57","data":{"name":"PHP","description":"PHP Hypertext Processor programming language conferences."},"fields":{"slug":"conferences/php"}}]}}},{"node":{"id":"d08b2487-655f-5f7f-bff7-72899411d0a9","data":{"name":"AWS Community Day - June 2021","event_url":"https://splashthat.com","location":"Online","event_start_date":"2021-06-10","cfp_due_date":"2021-05-05","cfp_url":"https://sessionize.com/aws-community-day-2021/","event_end_date":"2021-06-10","twitter":null,"perks_checked":null,"region":"Americas","subregion":"Northern America","icon":[{"url":"https://dl.airtable.com/.attachments/f7733fad34771735482098d9ca1a220c/05cdfe4d/splashthat.com"}],"city":"Alice","country":"United States","created_date":"2021-03-23T00:21:08.000Z","created_days_back":31,"cfp_days_until":11,"is_new":0,"description":"Splash’s event marketing platform helps companies market, manage, and measure their live, virtual, and hybrid event programs. All on one platform.","travel_covered":null,"hotel_covered":null,"stipend_covered":null,"record_id":"rec3ODlMwdU9oO5Iz","category":[{"id":"17bb4611-8120-5f31-9bd1-7eabfa555d30","data":{"name":"General","description":"Conferences covering a wide range of web development and software engineering topics."},"fields":{"slug":"conferences/general"}}]}}},{"node":{"id":"ac204d5a-03e5-59c0-b330-c19e171e91aa","data":{"name":"PyCon India 2021","event_url":"https://in.pycon.org/2021/","location":"Virtual","event_start_date":"2021-09-17","cfp_due_date":"2021-05-07","cfp_url":"https://in.pycon.org/cfp/2021/proposals/","event_end_date":null,"twitter":null,"perks_checked":null,"region":null,"subregion":null,"icon":[{"url":"https://dl.airtable.com/.attachments/0a9b16e92bccbea6f9bdbb5f36646ed4/44d29508/pycon.org"}],"city":null,"country":null,"created_date":"2021-04-15T09:42:04.000Z","created_days_back":7,"cfp_days_until":13,"is_new":0,"description":"PyCon India is the largest gathering of Pythonistas in India for the Python programming language. The 13th edition of PyCon India will be taking place online from 17th September to 20th September 2021. With this unique scenario at hand, we plan to make this year’s conference bigger, better, an…","travel_covered":null,"hotel_covered":null,"stipend_covered":null,"record_id":"recsHL8WYBISJJvEE","category":[{"id":"2f707d71-008b-5aef-881e-eba8ae5fbcee","data":{"name":"Python","description":"Python programming language conferences."},"fields":{"slug":"conferences/python"}}]}}},{"node":{"id":"3fa640f2-f05c-5de1-9a40-316189d6d69b","data":{"name":"DevSecOps Days Pittsburgh 2021","event_url":"https://resources.sei.cmu.edu/news-events/events/devsecops","location":"Online","event_start_date":"2021-06-16","cfp_due_date":"2021-05-07","cfp_url":"https://sessionize.com/devsecops-days-pittsburgh-2021/","event_end_date":"2021-06-16","twitter":null,"perks_checked":null,"region":"Americas","subregion":"Northern America","icon":[{"url":"https://dl.airtable.com/.attachments/ede4c9527bbfacb0e5ffd772ea946caa/d34321c2/cmu.edu"}],"city":"Alice","country":"United States","created_date":"2021-04-13T04:21:05.000Z","created_days_back":9,"cfp_days_until":13,"is_new":0,"description":"DevSecOps Days 2021","travel_covered":null,"hotel_covered":null,"stipend_covered":null,"record_id":"reckBhZuCp8l273Z3","category":[{"id":"3006c0c1-819e-5478-946a-37c2c2c98242","data":{"name":"Security","description":"Information and application security conferences."},"fields":{"slug":"conferences/security"}}]}}},{"node":{"id":"d6f9998e-3119-5492-a468-e5aad139dd93","data":{"name":"GoWest Conference - 2021","event_url":"https://www.gowestconf.com","location":"Utah/Remote","event_start_date":"2021-10-22","cfp_due_date":"2021-05-07","cfp_url":"https://papercall.io/cfps/3746/submissions/new","event_end_date":"2021-10-22","twitter":null,"perks_checked":null,"region":null,"subregion":null,"icon":[{"url":"https://dl.airtable.com/.attachments/9daf020ebcc381997a6a48f791f3bd3c/df7802ce/4ee7be_3a66139fdf3c460c83377f06dfcf04abmv2.png"}],"city":null,"country":"Online","created_date":"2021-04-07T04:20:39.000Z","created_days_back":15,"cfp_days_until":13,"is_new":0,"description":"The GoWest Conference was created with two main goals: to highlight the local talent and expertise in engineering with the Go programming language, and to bring world-renowned Go speakers to the area. This conference is meant to service the Rocky Mountain West Area (Arizona, Utah, Colorado, Idaho).","travel_covered":null,"hotel_covered":null,"stipend_covered":null,"record_id":"recnP5FDRJvGL42th","category":[{"id":"c89af0ba-bd5f-5eb3-9ad2-b5f84ca83660","data":{"name":"Go","description":"Go programming language conferences."},"fields":{"slug":"conferences/go"}}]}}},{"node":{"id":"b8d4e4fc-74ef-5e08-8c41-4534cc67050f","data":{"name":"TechStrong Con","event_url":"https://www.mediaopsevents.com/techstrongcon","location":"Online","event_start_date":"2021-06-02","cfp_due_date":"2021-05-07","cfp_url":"https://sessionize.com/techstrong-con/","event_end_date":"2021-06-02","twitter":null,"perks_checked":null,"region":"Americas","subregion":"Northern America","icon":[{"url":"https://dl.airtable.com/.attachments/a5244c8ad4020fbf521a359b44746da6/519ab578/967621-60542984b12c9.svg"}],"city":"Alice","country":"United States","created_date":"2021-03-26T00:20:30.000Z","created_days_back":28,"cfp_days_until":13,"is_new":0,"description":"TechStrong Con is a testament to the ways in which technology can improve human existence, even in our greatest time of need. This year’s event will feature examples of how digital transformation, DevOps, cloud native and cybersecurity have enabled us to survive—and some thrive—in the past year, and…","travel_covered":null,"hotel_covered":null,"stipend_covered":null,"record_id":"recXENodMOiYUod6F","category":[{"id":"3db9c63a-a3f0-5e6d-87a8-13219235bfbb","data":{"name":"DevOps","description":"Developer Operations centered conferences."},"fields":{"slug":"conferences/devops"}}]}}},{"node":{"id":"3aa37291-3b47-50f5-8213-eb78c608ee88","data":{"name":"Bergen Microsoft Community  - June 2021","event_url":"https://bergenmicrosoftcommunity.one","location":"Online","event_start_date":"2021-06-02","cfp_due_date":"2021-05-07","cfp_url":"https://sessionize.com/bergen-microsoft-community----june-2021/","event_end_date":"2021-06-02","twitter":null,"perks_checked":null,"region":"Americas","subregion":"Northern America","icon":[{"url":"https://dl.airtable.com/.attachments/1c7575e719f408bb386cff29baa3338b/03a11d75/banner-img.jpg"}],"city":"Alice","country":"United States","created_date":"2021-03-26T00:20:30.000Z","created_days_back":28,"cfp_days_until":13,"is_new":0,"description":"Vi er en gruppe tekniske og ikke tekniske ressurser som synes det er på høy tid at Norges nest største by klarer å stable på beina en aktiv brukergruppe, som kan være et sted der vi hjelper hverandre og deler vår kunnskap på tvers av ulike selskaper og bransjer. Fellesnevneren er “Microsoft teknolog…","travel_covered":null,"hotel_covered":null,"stipend_covered":null,"record_id":"recLfdy6PStnkNTEK","category":[{"id":"17bb4611-8120-5f31-9bd1-7eabfa555d30","data":{"name":"General","description":"Conferences covering a wide range of web development and software engineering topics."},"fields":{"slug":"conferences/general"}}]}}},{"node":{"id":"3cb8c5fa-1514-5053-bfff-a4319ad8e728","data":{"name":"Global Maintainer Summit 2021","event_url":"https://globalmaintainersummit.github.com","location":"Online","event_start_date":"2021-06-07","cfp_due_date":"2021-05-08","cfp_url":"https://sessionize.com/global-maintainer-summit-2021/","event_end_date":"2021-06-07","twitter":null,"perks_checked":null,"region":"Americas","subregion":"Northern America","icon":[{"url":"https://dl.airtable.com/.attachments/77bc545e203c1672e6579791a761fd57/24b71298/github.com"}],"city":"Alice","country":"United States","created_date":"2021-04-02T04:20:48.000Z","created_days_back":20,"cfp_days_until":14,"is_new":0,"description":"A virtual gathering for the maintainers that make open source possible.","travel_covered":null,"hotel_covered":null,"stipend_covered":null,"record_id":"recwrIjExfd3dSxpH","category":[{"id":"17bb4611-8120-5f31-9bd1-7eabfa555d30","data":{"name":"General","description":"Conferences covering a wide range of web development and software engineering topics."},"fields":{"slug":"conferences/general"}}]}}},{"node":{"id":"4f35bc0e-43c6-5d4e-89a5-7b0607dca052","data":{"name":"DevSecCon24 2021","event_url":"https://www.devseccon.com","location":"Online","event_start_date":"2021-06-23","cfp_due_date":"2021-05-08","cfp_url":"https://sessionize.com/devseccon24-2021/","event_end_date":"2021-06-23","twitter":null,"perks_checked":null,"region":"Americas","subregion":"Northern America","icon":[{"url":"https://dl.airtable.com/.attachments/a009c9e3a69c5f564f0cc1e75104bc93/64b6917e/devseccon.com"}],"city":"Alice","country":"United States","created_date":"2021-04-02T04:20:48.000Z","created_days_back":20,"cfp_days_until":14,"is_new":0,"description":"DevSecCon is the global community dedicated to DevSecOps - with the goal of bringing development, operations and security teams together to meet, learn and collaborate on the best and brightest approaches to secure development.","travel_covered":null,"hotel_covered":null,"stipend_covered":null,"record_id":"recKGcgR0FoB7j0CZ","category":[{"id":"3006c0c1-819e-5478-946a-37c2c2c98242","data":{"name":"Security","description":"Information and application security conferences."},"fields":{"slug":"conferences/security"}}]}}},{"node":{"id":"15efa817-a727-5f6b-89a5-4dc6a1ee82fd","data":{"name":"W4TT Anfitrionas Hablemos de tecnología","event_url":"https://women4tt.blogspot.com","location":"Online","event_start_date":"2021-06-18","cfp_due_date":"2021-05-08","cfp_url":"https://sessionize.com/w4tt-anfitrionas-hablemos-de-tecnologia/","event_end_date":"2021-06-18","twitter":null,"perks_checked":null,"region":"Americas","subregion":"Northern America","icon":[{"url":"https://dl.airtable.com/.attachments/d4ee835ab757c9b56d47c38df6f5bc27/fcd5042a/icon18_wrench_allbkg.png"}],"city":"Alice","country":"United States","created_date":"2021-03-27T00:21:50.000Z","created_days_back":27,"cfp_days_until":14,"is_new":0,"description":"📢 ¡Abrimos el Call 4 Speakers para nuestro próximo evento!","travel_covered":null,"hotel_covered":null,"stipend_covered":null,"record_id":"recWtGF0d4MnFkUSL","category":[{"id":"17bb4611-8120-5f31-9bd1-7eabfa555d30","data":{"name":"General","description":"Conferences covering a wide range of web development and software engineering topics."},"fields":{"slug":"conferences/general"}}]}}},{"node":{"id":"d7b3ce6f-fe58-5a86-996d-c0763508f917","data":{"name":"Be Connected day 19th May 2021","event_url":"https://www.beconnectedday.it","location":"Online","event_start_date":"2021-05-19","cfp_due_date":"2021-05-08","cfp_url":"https://sessionize.com/be-connected-day-19th-May-2021/","event_end_date":"2021-05-19","twitter":null,"perks_checked":null,"region":"Americas","subregion":"Northern America","icon":[{"url":"https://dl.airtable.com/.attachments/c60945664efdeeb1d4e53bcb2f18cb9d/d2abd3ea/BDG_LOGO_NoText.jpg"}],"city":"Alice","country":"United States","created_date":"2021-03-26T00:20:29.000Z","created_days_back":28,"cfp_days_until":14,"is_new":0,"description":"-","travel_covered":null,"hotel_covered":null,"stipend_covered":null,"record_id":"recEeioeKbQVJtbHQ","category":[{"id":"17bb4611-8120-5f31-9bd1-7eabfa555d30","data":{"name":"General","description":"Conferences covering a wide range of web development and software engineering topics."},"fields":{"slug":"conferences/general"}}]}}},{"node":{"id":"846650fc-0593-5232-88f5-8891aa18c0b1","data":{"name":"IT-Tage 2021 Remote","event_url":"https://www.it-tage.org","location":"Remote","event_start_date":"2021-12-06","cfp_due_date":"2021-05-10","cfp_url":"https://www.it-tage.org/cfp","event_end_date":null,"twitter":null,"perks_checked":null,"region":null,"subregion":null,"icon":[{"url":"https://dl.airtable.com/.attachments/9ab6413289088e7f521a0623178060c5/e8af6361/informatik-aktuell.de"}],"city":null,"country":"Online","created_date":"2021-03-11T08:36:58.000Z","created_days_back":42,"cfp_days_until":16,"is_new":0,"description":"Die IT-Tage 365 bieten mit über 200 Sessions On-Demand eine große Bandbreite an aktuellen Entwickler-, Architektur- und IT-Managementthemen. Zudem finden regelmäßig neue Remote-Sessions statt.","travel_covered":null,"hotel_covered":null,"stipend_covered":null,"record_id":"recDqiBv45dsaRJey","category":[{"id":"17bb4611-8120-5f31-9bd1-7eabfa555d30","data":{"name":"General","description":"Conferences covering a wide range of web development and software engineering topics."},"fields":{"slug":"conferences/general"}}]}}},{"node":{"id":"9c5e942e-1241-5c48-9d6e-d56201ce3045","data":{"name":"QuBit Conference Prague 2021","event_url":"https://prague.qubitconference.com/","location":"Prague, Czech Republic","event_start_date":"2021-06-02","cfp_due_date":"2021-05-10","cfp_url":"https://prague.qubitconference.com/call-speakers-form-prague/","event_end_date":null,"twitter":null,"perks_checked":null,"region":"Europe","subregion":"Eastern Europe","icon":[{"url":"https://dl.airtable.com/.attachments/b4316edd734cbb1587e9c61e4f1c6fa6/18d07321/qubitconference.com"}],"city":"Prague","country":"Czechia","created_date":"2020-11-06T13:49:13.000Z","created_days_back":167,"cfp_days_until":16,"is_new":0,"description":"QuBit Conference Prague 2020, a cybersecurity community event, taking place in Prague, Czech Republic, 23 – 24 September 2020. Join QuBit Conference today!","travel_covered":null,"hotel_covered":null,"stipend_covered":null,"record_id":"recxUFiDm96gbI4ZR","category":[{"id":"3006c0c1-819e-5478-946a-37c2c2c98242","data":{"name":"Security","description":"Information and application security conferences."},"fields":{"slug":"conferences/security"}}]}}},{"node":{"id":"9aab1eca-427a-5da8-ace5-a2e2e65c2d58","data":{"name":"iSAQB Software Architecture Gathering 2021","event_url":"https://skillsmatter.com","location":"Online","event_start_date":"2021-10-11","cfp_due_date":"2021-05-12","cfp_url":"https://sessionize.com/skillsmatter-isaqb-sag2021/","event_end_date":"2021-10-11","twitter":null,"perks_checked":null,"region":"Americas","subregion":"Northern America","icon":[{"url":"https://dl.airtable.com/.attachments/8bf1750e220cd6b6eff98a3fa77b945e/e8427b51/skillsmatter.com"}],"city":"Alice","country":"United States","created_date":"2021-04-10T04:20:37.000Z","created_days_back":12,"cfp_days_until":18,"is_new":0,"description":"Join our community to learn and share skills with thousands of developers passionate about software craftsmanship.","travel_covered":null,"hotel_covered":null,"stipend_covered":null,"record_id":"rec1OPBrlzK3C7Guy","category":[{"id":"17bb4611-8120-5f31-9bd1-7eabfa555d30","data":{"name":"General","description":"Conferences covering a wide range of web development and software engineering topics."},"fields":{"slug":"conferences/general"}}]}}},{"node":{"id":"cc131fa2-8540-5792-8435-37c72bdaa6d1","data":{"name":"@PowerBIEspanol Virtual Conf 2021 Primavera","event_url":"https://powerbiespanolvirtualconf2021primavera.azurewebsites.net","location":"Online","event_start_date":"2021-06-01","cfp_due_date":"2021-05-14","cfp_url":"https://sessionize.com/powerbi-espanol-virtual-conf-2021-primavera/","event_end_date":"2021-06-01","twitter":null,"perks_checked":null,"region":"Americas","subregion":"Northern America","icon":[{"url":"https://dl.airtable.com/.attachments/b77c0fa9abe0c5b5687cd4fcbb3dc7f0/4421e6ab/w-logo-blue-white-bg.png"}],"city":"Alice","country":"United States","created_date":"2021-04-14T04:21:30.000Z","created_days_back":8,"cfp_days_until":20,"is_new":0,"description":"Segunda edición de la @PowerBIEspanol Virtual Conf 2021 (Edición Primavera): Después de que más de 2000 personas disfrutasen de la primera edición, volvemos con el mejor evento de PowerBI del año, con más charlas, más conocimiento y más ganas que nunca. ¡Regístrate aquí para acceder al evento en viv…","travel_covered":null,"hotel_covered":null,"stipend_covered":null,"record_id":"rec3VbkrvJmZRxgj4","category":[{"id":"17bb4611-8120-5f31-9bd1-7eabfa555d30","data":{"name":"General","description":"Conferences covering a wide range of web development and software engineering topics."},"fields":{"slug":"conferences/general"}}]}}},{"node":{"id":"4068dff4-2043-516e-8c93-5cbdb9b13385","data":{"name":".debug 2021","event_url":"https://www.debug.hr","location":"Zagreb, City of Zagreb, Croatia","event_start_date":"2021-06-10","cfp_due_date":"2021-05-14","cfp_url":"https://sessionize.com/4d59435422054632b605421945ccbd72/","event_end_date":"2021-06-10","twitter":null,"perks_checked":null,"region":"Europe","subregion":"Southern Europe","icon":[{"url":"https://dl.airtable.com/.attachments/717288be193bee9ff7fc063a1d84b6fc/92d78a34/cropped-icon-270x270.png"}],"city":"Zagreb","country":"Croatia","created_date":"2021-04-02T00:21:34.000Z","created_days_back":21,"cfp_days_until":20,"is_new":0,"description":"Developers Conference by Bug - Zagreb, 10-11 June 2021","travel_covered":null,"hotel_covered":null,"stipend_covered":null,"record_id":"reczG5HcRQtMO748W","category":[{"id":"17bb4611-8120-5f31-9bd1-7eabfa555d30","data":{"name":"General","description":"Conferences covering a wide range of web development and software engineering topics."},"fields":{"slug":"conferences/general"}}]}}}]}},"pageContext":{"isCreatedByStatefulCreatePages":true,"greaterThanDate":"2021-04-23","lessThanDate":"2021-05-14"}}