{"data":{"site":{"meta":{"title":"CFP Land","description":"Calls for Proposals, Tech Conferences, and Speaking Tips","url":"https://www.cfpland.com","author":"Karl L. Hughes","twitter":"cfp_land","image":"/img/default.png"}},"conferences":{"edges":[{"node":{"id":"c7e30496-14e1-5840-b3b5-2f82739061a2","data":{"name":"GopherCon Europe","event_url":"https://gophercon.berlin","location":"Berlin, Germany","event_start_date":"2020-04-23","cfp_due_date":"2020-01-12","cfp_url":"https://www.papercall.io/gophercon-eu-2020","event_end_date":"2020-04-26","twitter":"@gopherconEU","perks_checked":true,"region":"Europe","subregion":"Western Europe","icon":[{"url":"https://dl.airtable.com/.attachments/aa568050ded36f38ccfacd5bd08de0ea/18b050db/gophercon.berlin"}],"city":"Berlin","country":"Germany","created_date":"2019-11-30T00:20:58.000Z","created_days_back":79,"cfp_days_until":-36,"is_new":0,"description":"GopherCon Europe 2020 in Berlin","travel_covered":true,"hotel_covered":true,"stipend_covered":null,"record_id":"receVqEhMaNPd8ZnE","category":[{"id":"c89af0ba-bd5f-5eb3-9ad2-b5f84ca83660","data":{"name":"Go","description":"Go programming language conferences."},"fields":{"slug":"conferences/go"}}]}}}]}},"pageContext":{"isCreatedByStatefulCreatePages":false,"recordId":"receVqEhMaNPd8ZnE","relatedRecords":[{"name":"dotGo","event_url":"https://www.dotgo.eu","location":"Paris, France","event_start_date":"2020-03-30","cfp_due_date":"2020-01-01","cfp_url":"https://www.dotconferences.com/cfp","event_end_date":"2020-03-30","twitter":"@dotgoeu","perks_checked":true,"region":"Europe","subregion":"Western Europe","icon":[{"url":"https://dl.airtable.com/.attachments/49fffbc60dd03525dbad939bf289f039/efd4e9c5/favicon.png"}],"country":"France","created_date":"2019-11-19T00:20:33.000Z","created_days_back":90,"cfp_days_until":-47,"is_new":0,"description":"The European Go conference • March 30, 2020 • Paris, France","travel_covered":null,"hotel_covered":null,"stipend_covered":null,"record_id":"recD4yX23XL0mwbQz","category":[{"id":"c89af0ba-bd5f-5eb3-9ad2-b5f84ca83660","data":{"name":"Go","description":"Go programming language conferences."},"fields":{"slug":"conferences/go"}}],"score":0},{"name":"GoWayFest 3.0","event_url":"https://goway.io","location":"Minsk, Belarus","event_start_date":"2019-07-05","cfp_due_date":"2019-05-20","cfp_url":"https://papercall.io/cfps/2171/submissions/new","event_end_date":"2019-07-05","twitter":null,"perks_checked":true,"region":"Europe","subregion":"Eastern Europe","icon":[{"url":"https://dl.airtable.com/.attachments/0fa035552aef34540a04c5bbae2a3a5f/845f4566/Asset_12x.png"}],"country":"Belarus","created_date":"2019-05-12T09:00:12.000Z","created_days_back":281,"cfp_days_until":-273,"is_new":0,"description":"July 5, 2019 | The first of a kind event in Eastern Europe fully dedicated to Go","travel_covered":true,"hotel_covered":true,"stipend_covered":null,"record_id":"rec7fUtHXnUlBs4WX","category":[{"id":"c89af0ba-bd5f-5eb3-9ad2-b5f84ca83660","data":{"name":"Go","description":"Go programming language conferences."},"fields":{"slug":"conferences/go"}}],"score":0},{"name":"FrOSCon","event_url":"https://www.froscon.de","location":"Sankt Augustin, Germany","event_start_date":"2019-08-10","cfp_due_date":"2019-05-23","cfp_url":"https://www.froscon.de/en/cfp/cfpapers","event_end_date":"2019-08-11","twitter":null,"perks_checked":true,"region":"Europe","subregion":"Western Europe","icon":null,"country":"Germany","created_date":"2019-04-22T03:05:11.000Z","created_days_back":301,"cfp_days_until":-270,"is_new":0,"description":"Freie Software und Open Source - das sind die Themen der FrOSCon. Jedes Jahr im Spätsommer veranstaltet der Fachbereich Informatik der Hochschule Bonn-Rhein-Sieg mit Hilfe des FrOSCon e.V. ein spannendes Programm mit Vorträgen und Workshops für Besucher aller Altersklassen, die Freie Software nutzen…","travel_covered":true,"hotel_covered":null,"stipend_covered":null,"record_id":"recrZN6yAiRjHGvkA","category":[{"id":"17bb4611-8120-5f31-9bd1-7eabfa555d30","data":{"name":"General","description":"Conferences covering a wide range of web development and software engineering topics."},"fields":{"slug":"conferences/general"}}],"score":0},{"name":"JVM Con","event_url":"https://www.jvm-con.de","location":"Cologne, Germany","event_start_date":"2019-11-25","cfp_due_date":"2019-05-24","cfp_url":"https://docs.google.com/forms/d/e/1FAIpQLSen0DZnN8pbJdfmBi7Q6T-tR5J3L_fKdN4QkAg09SMWi_bvDw/viewform","event_end_date":"2019-11-27","twitter":null,"perks_checked":true,"region":"Europe","subregion":"Western Europe","icon":[{"url":"https://dl.airtable.com/.attachments/566d89b0537e10f50c8d20212ff49737/90359aeb/jvm-icon-200x200.png"}],"country":"Germany","created_date":"2019-04-23T03:07:22.000Z","created_days_back":300,"cfp_days_until":-269,"is_new":0,"description":"Hier finden Sie die Programme der letzten Jahre im Überblick.","travel_covered":null,"hotel_covered":null,"stipend_covered":null,"record_id":"recKIcFdQk5Ja6hkE","category":[{"id":"5397a316-d186-5896-9dca-24ef439e4dd7","data":{"name":"Java","description":"Java programming language conferences."},"fields":{"slug":"conferences/java"}}],"score":0}]}}