{"data":{"site":{"meta":{"title":"CFP Land","description":"Calls for Proposals, Tech Conferences, and Speaking Tips","url":"https://www.cfpland.com","author":"Karl L. Hughes","twitter":"cfp_land","image":"/img/default.png"}},"category":{"edges":[{"node":{"id":"526da865-5b6e-524b-942e-240033174fda","data":{"name":".NET","description":".NET and C# programming language conferences."}}}]},"conferences":{"edges":[{"node":{"id":"fd74550f-c541-5cfd-870d-412f08e751b1","data":{"name":"IcingaConf","event_url":"http://www.icingaconf.com","location":"Amsterdam, Niederlande","event_start_date":"2020-05-12","cfp_due_date":"2020-01-31","cfp_url":"https://icingaconf.com/propose","event_end_date":"2020-05-14","twitter":"@icinga","perks_checked":true,"region":"Europe","subregion":"Western Europe","icon":[{"url":"https://dl.airtable.com/.attachments/dfdab5a5520fd129933e47494cdb2a6a/4bfcc619/icingaconf.com"}],"country":"Netherlands","created_date":"2019-12-19T00:20:40.000Z","created_days_back":22,"cfp_days_until":20,"is_new":0,"description":"IcingaConf is a platform where monitoring enthusiasts come together to share and learn about their experiences and challenges.","travel_covered":null,"hotel_covered":null,"stipend_covered":null,"record_id":"recvdZ5PmfhStjhf8","category":[{"id":"526da865-5b6e-524b-942e-240033174fda","data":{"name":".NET","description":".NET and C# programming language conferences."},"fields":{"slug":"conferences/.net"}}]}}}]}},"pageContext":{"isCreatedByStatefulCreatePages":false,"slug":"conferences/.net"}}