{"data":{"site":{"meta":{"title":"CFP Land","description":"Calls for Proposals, Tech Conferences, and Speaking Tips","url":"https://www.cfpland.com","author":"Karl L. Hughes","twitter":"cfp_land","image":"/img/default.png"}},"conferences":{"edges":[{"node":{"id":"9950f35b-25c6-5850-82cf-86276a7eb8ad","data":{"name":"IoT Innovatech Digital 2020","event_url":"https://iotinnovatech.com","location":"Virtual Event","event_start_date":"2020-09-07","cfp_due_date":"2020-04-06","cfp_url":"https://sessionize.com/IoTInnovatech2020/","event_end_date":"2020-09-07","twitter":null,"perks_checked":true,"region":null,"subregion":null,"icon":[{"url":"https://dl.airtable.com/.attachments/a34ee4f7b9a61b01ccb39bbb4f78b74a/3dd306f0/iotinnovatech.com"}],"city":null,"country":"Online","created_date":"2020-03-24T04:21:07.000Z","created_days_back":83,"cfp_days_until":-70,"is_new":0,"description":"IoT Innovatech es el evento de IoT Industrial más completo en Latinoamérica donde se reúnen las industrias claves de la región con la comunidad global del IoT.","travel_covered":null,"hotel_covered":null,"stipend_covered":null,"record_id":"rec7gWyUtjH2zPMe0","category":[{"id":"17bb4611-8120-5f31-9bd1-7eabfa555d30","data":{"name":"General","description":"Conferences covering a wide range of web development and software engineering topics."},"fields":{"slug":"conferences/general"}}]}}}]}},"pageContext":{"isCreatedByStatefulCreatePages":false,"recordId":"rec7gWyUtjH2zPMe0","relatedRecords":[{"name":"Dev Around the Sun","event_url":"https://devaroundthesun.org","location":"Online and Everywhere","event_start_date":"2020-05-12","cfp_due_date":"2020-05-01","cfp_url":"https://sessionize.com/dev-around-the-sun/","event_end_date":"2020-05-12","twitter":null,"perks_checked":true,"region":null,"subregion":null,"icon":[{"url":"https://dl.airtable.com/.attachments/90391a95284f2a395c566491a1b1fb88/ea6648b9/favicon.ico"}],"country":"Online","created_date":"2020-04-11T04:21:13.000Z","created_days_back":65,"cfp_days_until":-45,"is_new":0,"description":"-","travel_covered":null,"hotel_covered":null,"stipend_covered":null,"record_id":"recfAhW1PBBCup47E","category":[{"id":"17bb4611-8120-5f31-9bd1-7eabfa555d30","data":{"name":"General","description":"Conferences covering a wide range of web development and software engineering topics."},"fields":{"slug":"conferences/general"}}],"score":10},{"name":"Global Online Azure Bootcamp 2020","event_url":"https://globalonlineazurebootcamp.wordpress.com","location":"YouTube","event_start_date":"2020-04-23","cfp_due_date":"2020-03-21","cfp_url":"https://sessionize.com/global-online-azure-bootcamp-2020/","event_end_date":"2020-04-23","twitter":null,"perks_checked":true,"region":null,"subregion":null,"icon":[{"url":"https://dl.airtable.com/.attachments/72355dea81f53861565b03ca246e9075/13754670/wordpress.com"}],"country":"Online","created_date":"2020-03-06T04:20:29.000Z","created_days_back":101,"cfp_days_until":-86,"is_new":0,"description":"An ONLINE community event to learn about Microsoft Azure","travel_covered":null,"hotel_covered":null,"stipend_covered":null,"record_id":"recYUqwASXmACUexh","category":[{"id":"17bb4611-8120-5f31-9bd1-7eabfa555d30","data":{"name":"General","description":"Conferences covering a wide range of web development and software engineering topics."},"fields":{"slug":"conferences/general"}}],"score":10},{"name":"Open Source Community Conference(OSCONF) 2020 Pune","event_url":"https://osconf.collabnix.com","location":"Virtual Online Event","event_start_date":"2020-05-16","cfp_due_date":"2020-05-11","cfp_url":"https://papercall.io/cfps/3236/submissions/new","event_end_date":"2020-05-16","twitter":null,"perks_checked":true,"region":null,"subregion":null,"icon":[{"url":"https://dl.airtable.com/.attachments/1867635ebe84e39b9db0ebe68deafdcc/97108f8c/collabnix.com"}],"country":"Online","created_date":"2020-05-03T04:20:34.000Z","created_days_back":43,"cfp_days_until":-35,"is_new":0,"description":"OSCONF is a platform built to connect & bring all leading Meetup communities, Cloud native experts, Evangelists & DevOps together under one roof. It is a non-profit community event which allows you to interact with community leaders, ambassadors & open community contributors.","travel_covered":null,"hotel_covered":null,"stipend_covered":null,"record_id":"recc5yTEgyAspHRLI","category":[{"id":"17bb4611-8120-5f31-9bd1-7eabfa555d30","data":{"name":"General","description":"Conferences covering a wide range of web development and software engineering topics."},"fields":{"slug":"conferences/general"}}],"score":10},{"name":"Global Azure Bootcamp Pakistan","event_url":"https://cccpak.com","location":"Virtual Event","event_start_date":"2020-04-25","cfp_due_date":"2020-03-25","cfp_url":"https://sessionize.com/cccpak/","event_end_date":"2020-04-25","twitter":null,"perks_checked":true,"region":null,"subregion":null,"icon":[{"url":"https://dl.airtable.com/.attachments/6bdeaa458c8abbe35728669a2a4f11c3/561445cb/f31b46611473a20f56445bd3b24df116"}],"country":"Online","created_date":"2020-03-05T04:20:29.000Z","created_days_back":102,"cfp_days_until":-82,"is_new":0,"description":"-","travel_covered":null,"hotel_covered":null,"stipend_covered":null,"record_id":"recM6ZLDXEyGxhSwW","category":[{"id":"17bb4611-8120-5f31-9bd1-7eabfa555d30","data":{"name":"General","description":"Conferences covering a wide range of web development and software engineering topics."},"fields":{"slug":"conferences/general"}}],"score":10}]}}